{
    "AX": {
        "error": 0.008490564990305023,
        "error_type": "SEM",
        "filter_outliers_dict": {
            "filter_outliers": true,
            "iterations": 1,
            "std_devs": 3,
            "use_iqr_filtering": false,
            "use_standard_deviation_filtering": false
        },
        "fit": "average",
        "fn": 35,
        "include_baseline_error": true,
        "modifier_error": 0.0,
        "modifier_value": 0.0,
        "n": 35,
        "outlier_excluded": [],
        "reviewed": true,
        "user_excluded": [],
        "value": 0.035293675865978
    },
    "CDD": {
        "error": 1.1246781450123817e-05,
        "error_type": "SEM",
        "filter_outliers_dict": {
            "filter_outliers": true,
            "iterations": 1,
            "std_devs": 10,
            "use_iqr_filtering": false,
            "use_standard_deviation_filtering": false
        },
        "fit": "average",
        "fn": 35,
        "include_baseline_error": true,
        "modifier_error": 1.0271657558355074e-05,
        "modifier_value": 2.389817591611198e-05,
        "n": 35,
        "outlier_excluded": [],
        "reviewed": true,
        "user_excluded": [],
        "value": 4.2731493678210035e-05
    },
    "H1": {
        "error": 0.0076173929108653065,
        "error_type": "SEM",
        "filter_outliers_dict": {
            "filter_outliers": true,
            "iterations": 1,
            "std_devs": 3,
            "use_iqr_filtering": false,
            "use_standard_deviation_filtering": false
        },
        "fit": "average",
        "fn": 35,
        "include_baseline_error": true,
        "modifier_error": 0.0,
        "modifier_value": 0.0,
        "n": 35,
        "outlier_excluded": [],
        "reviewed": true,
        "user_excluded": [],
        "value": -0.25972592192036764
    },
    "H2": {
        "error": 0.003365725849385138,
        "error_type": "SEM",
        "filter_outliers_dict": {
            "filter_outliers": true,
            "iterations": 1,
            "std_devs": 2
        },
        "fit": "average",
        "modifier_error": 0.0,
        "modifier_value": 0.0,
        "value": 0.10605298328395732
    },
    "L1": {
        "error": 0.004935404369904149,
        "error_type": "SEM",
        "filter_outliers_dict": {
            "filter_outliers": true,
            "iterations": 1,
            "std_devs": 3,
            "use_iqr_filtering": false,
            "use_standard_deviation_filtering": false
        },
        "fit": "average",
        "fn": 35,
        "include_baseline_error": true,
        "modifier_error": 0.0,
        "modifier_value": 0.0,
        "n": 35,
        "outlier_excluded": [],
        "reviewed": true,
        "user_excluded": [],
        "value": 0.0646627803798765
    },
    "L2": {
        "error": 0.0053821527137038905,
        "error_type": "SEM",
        "filter_outliers_dict": {
            "filter_outliers": true,
            "iterations": 1,
            "std_devs": 3,
            "use_iqr_filtering": false,
            "use_standard_deviation_filtering": false
        },
        "fit": "average",
        "fn": 35,
        "include_baseline_error": true,
        "modifier_error": 0.0,
        "modifier_value": 0.0,
        "n": 35,
        "outlier_excluded": [],
        "reviewed": true,
        "user_excluded": [],
        "value": -0.015883441888062018
    }
}